README.txt
setup.cfg
setup.py
tgext/__init__.py
tgext.command.egg-info/PKG-INFO
tgext.command.egg-info/SOURCES.txt
tgext.command.egg-info/dependency_links.txt
tgext.command.egg-info/entry_points.txt
tgext.command.egg-info/not-zip-safe
tgext.command.egg-info/top_level.txt
tgext/command/__init__.py
tgext/command/tgcommand.py