Metadata-Version: 1.0
Name: tgext.command
Version: 0.2
Summary: Cron-friendly TurboGears extension module
Home-page: http://www.vrplumber.com
Author: Mike C. Fletcher
Author-email: mcfletch@vrplumber.com
License: MIT
Keywords: TurboGears,command line,pid,paster
Platform: UNKNOWN
